{
  "$schema": "https://schema.management.azure.com/schemas/2019-04-01/deploymentTemplate.json#",
  "contentVersion": "1.0.0.0",
  "metadata": {
    "_generator": {
      "name": "bicep",
      "version": "0.38.33.27573",
      "templateHash": "9309744004058700244"
    }
  },
  "parameters": {
    "storageAccountName": {
      "type": "string",
      "defaultValue": "trngstor3kx5kjdzuqzq6"
    }
  },
  "variables": {
    "vnetName": "training-vnet",
    "azureFirewallSubnetName": "AzureFirewallSubnet",
    "firewallSubnetPrefix": "10.0.0.0/24"
  },
  "resources": [
    {
      "type": "Microsoft.Network/virtualNetworks/subnets",
      "apiVersion": "2023-09-01",
      "name": "[format('{0}/{1}', variables('vnetName'), variables('azureFirewallSubnetName'))]",
      "properties": {
        "addressPrefix": "[variables('firewallSubnetPrefix')]",
        "serviceEndpoints": [
          {
            "service": "Microsoft.Storage"
          }
        ]
      }
    },
    {
      "type": "Microsoft.Network/virtualNetworks/subnets",
      "apiVersion": "2023-09-01",
      "name": "[format('{0}/{1}', variables('vnetName'), 'VM3Subnet')]",
      "properties": {
        "addressPrefix": "10.0.4.0/24",
        "serviceEndpoints": []
      }
    },
    {
      "type": "Microsoft.Network/virtualNetworks/subnets",
      "apiVersion": "2023-09-01",
      "name": "[format('{0}/{1}', variables('vnetName'), 'VM4Subnet')]",
      "properties": {
        "addressPrefix": "10.0.5.0/24",
        "serviceEndpoints": []
      }
    },
    {
      "type": "Microsoft.Network/virtualNetworks/subnets",
      "apiVersion": "2023-09-01",
      "name": "[format('{0}/{1}', variables('vnetName'), 'VM5Subnet')]",
      "properties": {
        "addressPrefix": "10.0.6.0/24",
        "serviceEndpoints": []
      }
    },
    {
      "type": "Microsoft.Storage/storageAccounts",
      "apiVersion": "2023-01-01",
      "name": "[parameters('storageAccountName')]",
      "location": "[resourceGroup().location]",
      "kind": "StorageV2",
      "sku": {
        "name": "Standard_LRS"
      },
      "properties": {
        "networkAcls": {
          "bypass": "AzureServices",
          "defaultAction": "Deny",
          "virtualNetworkRules": [
            {
              "id": "[resourceId('Microsoft.Network/virtualNetworks/subnets', variables('vnetName'), variables('azureFirewallSubnetName'))]"
            }
          ]
        }
      },
      "dependsOn": [
        "[resourceId('Microsoft.Network/virtualNetworks/subnets', variables('vnetName'), variables('azureFirewallSubnetName'))]"
      ]
    }
  ]
}